delpinos/rabbitmq/channel.py
delpinos/rabbitmq/config.py
delpinos/rabbitmq/connection.py
delpinos/rabbitmq/consumer.py
delpinos/rabbitmq/exchange.py
delpinos/rabbitmq/functions.py
delpinos/rabbitmq/producer.py
delpinos/rabbitmq/queue.py
delpinos/rabbitmq/setup.py
delpinos_rabbitmq-0.0.4.dist-info/METADATA
delpinos_rabbitmq-0.0.4.dist-info/WHEEL
delpinos_rabbitmq-0.0.4.dist-info/top_level.txt
delpinos_rabbitmq-0.0.4.dist-info/RECORD
