Metadata-Version: 2.1
Name: delpinos-rabbitmq
Version: 0.0.4
Summary: Delpinos Rabbitmq - Delpinos Framework
Author-email: Alef Bruno Delpino de Oliveira <alef@delpinos.com>
Keywords: delpinos,rabbitmq
Classifier: Programming Language :: Python :: 3
Classifier: Programming Language :: Python :: 3.10
Classifier: Topic :: Software Development :: Libraries :: Python Modules
Requires-Python: >=3.10
Requires-Dist: delpinos-core >=0.0.3
Requires-Dist: pika >=1.3.2
